databricks_azure_ad_sync_provider/__init__.py
databricks_azure_ad_sync_provider/azure_identity.py
databricks_azure_ad_sync_provider/databricks_identity.py
databricks_azure_ad_sync_provider/main.py
databricks_azure_ad_sync_provider/one_way_match.py
databricks_azure_ad_sync_provider/sync_classes.py
databricks_azure_ad_sync_provider/yaml_parser.py
databricks_azure_ad_sync_provider-0.1.4.dist-info/METADATA
databricks_azure_ad_sync_provider-0.1.4.dist-info/WHEEL
databricks_azure_ad_sync_provider-0.1.4.dist-info/top_level.txt
databricks_azure_ad_sync_provider-0.1.4.dist-info/RECORD
