Metadata-Version: 2.1
Name: databricks-azure-ad-sync-provider
Version: 0.1.4
Summary: Default template for PDM package
Author-email: Nicolas <nicolas.jankelevitch@dataroots.io>, Bram <bram.decoster@dataroots.io>, Adrien <adrien@dataroots.io>, Xuyao <xuyao@dataroots.io>, Sam <sam@dataroots.io>
License: MIT
Requires-Python: ==3.9.*
Requires-Dist: azure-identity >=1.15.0
Requires-Dist: databricks-sdk >=0.17.0
Requires-Dist: msgraph-sdk >=1.0.0
Requires-Dist: ConfigParser >=6.0.0
Requires-Dist: pyyaml >=6.0.1
Requires-Dist: pytest >=7.4.4
